[{"name":"ZIP ACCENT WOOL GRANITE MINI SKIRT", "type":"skirts", "price":"18,570,000 VND", "image":"images/1.webp"},
    {"name":"SCULPTURAL MINI SKIRT", "type":"skirts", "price":"19,350,000 VND", "image":"images/2.webp"},
    {"name":"SAFETY PIN MAXI SKIRT", "type":"skirts", "price":"29,500,000 VND", "image":"images/3.webp"},
    {"name":"SAFETY PIN NAPPA LEATHER SKIRT", "type":"skirts", "price":"43,110,000 VND", "image":"images/4.jpg"},
    {"name":"MEDUSA SAFETY-PIN-T-SHIRT", "type":"shirt", "price":"26,520,000 VND", "image":"images/5.webp"},
    {"name":"EMBROIDERED ROSES T-SHIRT", "type":"shirt", "price":"15,580,000 VND", "image":"images/6.webp"},
    {"name":"ZIP ACCENT WOOL FLARED COAT", "type":"coat", "price":"79,880,000 VND", "image":"images/7.webp"},
    {"name":"ZIP ACCENT WOOL CAPE", "type":"coat", "price":"73,920,000 VND", "image":"images/8.webp"},
    {"name":"NAPPA LEATHER BIKER JACKET", "type":"coat", "price":"92,480,000 VND", "image":"images/9.webp"},
    {"name":"SAFETY PIN BELTED CRÊPE DE CHINE DRESS", "type":"dress", "price":"48,400,000 VND", "image":"images/10.webp"},
    {"name":"ZIP ACCENT NEOPRENE SLEEVELESS DRESS", "type":"dress", "price":"58,010,000 VND", "image":"images/11.webp"},
    {"name":"MEDUSA ACCENT KNIT DRESS", "type":"dress", "price":"23,760,000 VND", "image":"images/12.webp"},
    {"name":"SAFARI CRÊPE DE CHINE SHORTS", "type":"pants", "price":"17,240,000 VND", "image":"images/13.webp"},
    {"name":"ASYMMETRIC SILK EVENING DRESS", "type":"dress", "price":"70,600,000 VND", "image":"images/14.webp"},
    {"name":"SAFARI MINI DRESS", "type":"dress", "price":"49,720,000 VND", "image":"images/15.webp"},
    {"name":"MEDUSA MOTIF STRAIGHT LEG JEANS", "type":"pants", "price":"16,580,000 VND", "image":"images/16.webp"},
    {"name":"CASHMERE SWEATER", "type":"shirt", "price":"16,580,000 VND", "image":"images/17.webp"},
    {"name":"CADY MIDI SKIRT", "type":"skirts", "price":"20,220,000 VND", "image":"images/18.webp"}]
